oab_vapi_common_client-2.44.0-py3.12-nspkg.pth
com/vmware/__init__.py
com/vmware/cis_client.py
com/vmware/vapi_client.py
com/vmware/cis/__init__.py
com/vmware/cis/task_client.py
com/vmware/vapi/__init__.py
com/vmware/vapi/metadata_client.py
com/vmware/vapi/std_client.py
com/vmware/vapi/metadata/__init__.py
com/vmware/vapi/metadata/authentication_client.py
com/vmware/vapi/metadata/cli_client.py
com/vmware/vapi/metadata/metamodel_client.py
com/vmware/vapi/metadata/privilege_client.py
com/vmware/vapi/metadata/routing_client.py
com/vmware/vapi/metadata/authentication/__init__.py
com/vmware/vapi/metadata/authentication/service_client.py
com/vmware/vapi/metadata/metamodel/__init__.py
com/vmware/vapi/metadata/metamodel/resource_client.py
com/vmware/vapi/metadata/metamodel/service_client.py
com/vmware/vapi/metadata/privilege/__init__.py
com/vmware/vapi/metadata/privilege/service_client.py
com/vmware/vapi/metadata/routing/__init__.py
com/vmware/vapi/metadata/routing/service_client.py
com/vmware/vapi/std/__init__.py
com/vmware/vapi/std/activation_client.py
com/vmware/vapi/std/errors_client.py
com/vmware/vapi/std/interposition_client.py
com/vmware/vapi/std/introspection_client.py
com/vmware/vapi/std/routing_client.py
oab_vapi_common_client-2.44.0.dist-info/licenses/LICENSE.txt
oab_vapi_common_client-2.44.0.dist-info/METADATA
oab_vapi_common_client-2.44.0.dist-info/WHEEL
oab_vapi_common_client-2.44.0.dist-info/namespace_packages.txt
oab_vapi_common_client-2.44.0.dist-info/top_level.txt
oab_vapi_common_client-2.44.0.dist-info/RECORD
